README.rst
infmin_main.py
setup.py
infmin.egg-info/PKG-INFO
infmin.egg-info/SOURCES.txt
infmin.egg-info/dependency_links.txt
infmin.egg-info/entry_points.txt
infmin.egg-info/top_level.txt