Metadata-Version: 1.1
Name: infmin
Version: 0.1.4
Summary: Text file minimizing CLI tool
Home-page: https://github.com/Scottz0r/infmin
Author: Scott Clewell
Author-email: scott.clewell@gmail.com
License: MIT
Keywords: infmin file minimize
Platform: UNKNOWN
Classifier: Development Status :: 4 - Beta
Classifier: Intended Audience :: Developers
Classifier: Intended Audience :: Information Technology
Classifier: Topic :: Utilities
Classifier: License :: OSI Approved :: MIT License
Classifier: Programming Language :: Python :: 3
Classifier: Programming Language :: Python :: 3.3
Classifier: Programming Language :: Python :: 3.4
Classifier: Programming Language :: Python :: 3.5
